MANIFEST.in
README.md
setup.py
pyKriging/CrossValidation.py
pyKriging/GlobalSensitivity.py
pyKriging/__init__.py
pyKriging/coKriging.py
pyKriging/krige.py
pyKriging/matrixops.py
pyKriging/regressionkrige.py
pyKriging/samplingplan.py
pyKriging/testfunctions.py
pyKriging/utilities.py
pyKriging.egg-info/PKG-INFO
pyKriging.egg-info/SOURCES.txt
pyKriging.egg-info/dependency_links.txt
pyKriging.egg-info/not-zip-safe
pyKriging.egg-info/requires.txt
pyKriging.egg-info/top_level.txt
pyKriging/sampling_plans/lhc_2_10.pkl
pyKriging/sampling_plans/lhc_2_11.pkl
pyKriging/sampling_plans/lhc_2_12.pkl
pyKriging/sampling_plans/lhc_2_13.pkl
pyKriging/sampling_plans/lhc_2_14.pkl
pyKriging/sampling_plans/lhc_2_15.pkl
pyKriging/sampling_plans/lhc_2_16.pkl
pyKriging/sampling_plans/lhc_2_17.pkl
pyKriging/sampling_plans/lhc_2_18.pkl
pyKriging/sampling_plans/lhc_2_19.pkl
pyKriging/sampling_plans/lhc_2_20.pkl
pyKriging/sampling_plans/lhc_2_21.pkl
pyKriging/sampling_plans/lhc_2_22.pkl
pyKriging/sampling_plans/lhc_2_23.pkl
pyKriging/sampling_plans/lhc_2_24.pkl
pyKriging/sampling_plans/lhc_2_25.pkl
pyKriging/sampling_plans/lhc_2_26.pkl
pyKriging/sampling_plans/lhc_2_27.pkl
pyKriging/sampling_plans/lhc_2_28.pkl
pyKriging/sampling_plans/lhc_2_29.pkl
pyKriging/sampling_plans/lhc_2_30.pkl
pyKriging/sampling_plans/lhc_2_31.pkl
pyKriging/sampling_plans/lhc_2_32.pkl
pyKriging/sampling_plans/lhc_2_33.pkl
pyKriging/sampling_plans/lhc_2_34.pkl
pyKriging/sampling_plans/lhc_2_35.pkl
pyKriging/sampling_plans/lhc_2_36.pkl
pyKriging/sampling_plans/lhc_2_37.pkl
pyKriging/sampling_plans/lhc_2_38.pkl
pyKriging/sampling_plans/lhc_2_39.pkl
pyKriging/sampling_plans/lhc_2_40.pkl
pyKriging/sampling_plans/lhc_2_41.pkl
pyKriging/sampling_plans/lhc_2_42.pkl
pyKriging/sampling_plans/lhc_2_43.pkl
pyKriging/sampling_plans/lhc_2_44.pkl
pyKriging/sampling_plans/lhc_2_45.pkl
pyKriging/sampling_plans/lhc_2_46.pkl
pyKriging/sampling_plans/lhc_2_47.pkl
pyKriging/sampling_plans/lhc_2_48.pkl
pyKriging/sampling_plans/lhc_2_49.pkl
pyKriging/sampling_plans/lhc_2_50.pkl
pyKriging/sampling_plans/lhc_2_51.pkl
pyKriging/sampling_plans/lhc_2_52.pkl
pyKriging/sampling_plans/lhc_2_53.pkl
pyKriging/sampling_plans/lhc_2_54.pkl
