Metadata-Version: 1.0
Name: pyKriging
Version: 0.2.0
Summary: A Kriging Toolbox for Python
Home-page: http://www.pykriging.com
Author: Chris Paulson
Author-email: capaulson@gmail.com
License: UNKNOWN
Platform: UNKNOWN
